<?xml version="1.0" encoding="utf-8"?>
<odoo>
    <!-- Abandoned Cart Fetch Wizard Form -->
    <record id="view_zid_abandoned_cart_fetch_wizard" model="ir.ui.view">
        <field name="name">zid.abandoned.cart.fetch.wizard.form</field>
        <field name="model">zid.abandoned.cart.fetch.wizard</field>
        <field name="arch" type="xml">
            <form string="Fetch Abandoned Carts from Zid">
                <group>
                    <group>
                        <field name="zid_connector_id" options="{'no_create': True}"/>
                        <field name="min_cart_value"/>
                    </group>
                    <group>
                        <field name="date_from"/>
                        <field name="date_to"/>
                    </group>
                </group>
                <footer>
                    <button string="Fetch Carts" name="action_fetch_carts" type="object" class="btn-primary"/>
                    <button string="Cancel" class="btn-secondary" special="cancel"/>
                </footer>
            </form>
        </field>
    </record>
</odoo>
